{
"guafjunzlaxu57qqpudku2qw":["bclev","Brian Clevinger"],
"t2wov5v7yj46xe4tefbgrnrx":["bclaymoore","B. Clay Moore"],
"uhsyhxc3f46zlowr2fh6y7ki":["bclikesyou","bc likes you"],
"v454g5duthmuyqrxieobjiq6":["bclarkomp","Brian Clark"],
"5ybv4oajyulthtxlfnd6c6vd":"bclark",
"pyqeycthsynitvsval7yjvm4":["bclendinning","🇺🇦 Bill Clendinning"],
"5qd6jabkxvvzlrerzrnrqb5d":["bclew","Lew 🌈 "],
"fjfvhasy573zvbixh4ynp6g4":["bclavie","Benjamin Clavié"],
"xfhzthovoxtlrlfestovryf4":["bclinton","Bill Clinton"],
"g52d5vdi4qvlfahyxi2uowps":["bcleafsfan","Geoff"],
"sq5oz26zvhahzbpqnnajpey7":"bclintbe",
"m6eqodslu3uhujhjuwu5aorb":"bclemenzi",
"lmbctzq6gafaudekahtdzmay":"bclendenin",
"o5wwdma4hqiabpr6c6qval5d":"bcld.app",
"voooln7ggtzgl6h6tscd3xrp":["bcluxton","Brian Cluxton"],
"sxhooyh5c56ldurevs77vo5n":["bcl","Brigid (Connolly)Lucchesi"],
"mpidyvke27e3ojlxheufoe4e":"bclondon",
"g3vnilgjemwazkxfanwhbxx2":"bcline",
"gl26aoxjqtitkkrv7qurashf":"bclingan",
"zoqhovcw5i6nuwodahc7ii5i":["bclemwrites","brit "],
"eozmcwmytcr4slexsu5inlrh":"bclough",
"j5b3zpbvriurifyqn7bmffvq":["bclintonparody","Bill Clinton (Parody) 🎸 🎷 🥃"],
"vp3cy7rng7dsnfc7v6r654gf":["bclovelace","Brennan Lovelace"],
"q5vbbcrmaldrvr2ehhipp67l":"bclelandgt",
"pwvrwjrpfkc6umgufsblx6yf":"bcl400",
"3spnp6t4vj3epk2mrjl66beo":["bclarkcgchar","Brad"],
"nhoxcjc2w6ugi4pm4rj3tulh":["bclienesch","B.C. Lienesch"],
"we5sxupsye4a72qthj4tbm65":["bclehmann","Benjamin Lehmann"],
"ie5fhs27fe5efsm64cgo7gza":"bclowde",
"pgsvfku73ofhv5xbo4xv6jeh":"bclenzen",
"slr5hgnypiyw2mdfrzwu53k4":"bclair21",
"mm2w76qetin2ynx3hn2lvyl2":["del3bcl3","Clover"]
}
