{
"54v74jtrz4vngga57e5776nc":["bbmhlanga","Dhara B "],
"6j6hqa5yqfkd35kdbe2nbfwi":["bbmountain","Thane"],
"glk7bswjdhk3z5jx3u7bftz4":["bbmbx","m."],
"csw7pastsjb2y4gdfgwpoo3j":["bbmin","BB"],
"w452rodbchacvc277sclhg2h":["bbm","b/bm"],
"p5bx7gvjnpdyxg4ewt5jjvhz":"bbmike",
"tnzagih45jxpe2gnibk5qnhx":["bbmercy","✨️🌒Mercy🌘✨️"],
"3slltxk475mhb3zix36ajcsu":["bbmintie","Britta 🤍✨"],
"mv3g3m2vt4an2ljtkmznizpa":["bbmcginty","Group Captain Lionel Mandrake"],
"g2mawvedm6e47f75zxdka64z":["bbmsn11","ワヰ"],
"a4rxpqjnn53dwvdm55kt6cn4":["bbmolls","Molly"],
"uxjo4ycpuwjo75s55su5vovw":["bbmyosotis08","刹那"],
"hylstcokrdveahi7nxwq6s7n":["bbmiller","Bethan Briggs-Miller "],
"scqqx3plqk3c7dp55ilji6ks":["bbmoth","BBMOTH"],
"cddyudrzfwcmvn5prrzw7on3":"bbmg",
"dwuxnbh4pob6zdlzmq7nf6wp":["bbmolasses","coronal mass ejection "],
"kvhrjg62t2au3vvvwqwh4tpd":["bbmame","bbmame"],
"7qpgj6vyr4mb2xvnyxtcnocf":"bbmize",
"rh6wdyfd74fa43z3vuli3myt":["bbmagic","bbmagic"],
"l6ofvpq64ph35lldwasj2wwy":["bbmm","Bm"],
"6m3sj5ev2trcelt6jn4ljw6n":["bbmikej","bbmikej"],
"kvn3bejdpj3t7o3n2mulz6u2":["bbmezzy","Mezzy"],
"viqe4afxjxpfkp27a6xf5zf5":"bbmac227",
"2zral44smpwfhskkq5cfcbam":["bbmaeglutz","Constancette"],
"ntql2ymurxvi7g2qcp735tme":["bbmjest","정볨"],
"g6gg5z3kyn3xhtxqpdcts7z4":["blogbbm","Blog BBM"],
"7icdlc5zfb4i2p5e6n7mcwph":["boder","BBM"],
"zsf2esh3vpf7rvbicaq6f2x4":["bugra","bbm"],
"qdkoysa7mih6eqkb5wojdrys":["kmiya-bbm","miya"],
"tvmjewchpzw5qvig63ooiegj":["myngus","BBMyn"],
"tn4sbqo6655buh4pyi66cqzw":["palcomix","Bbmbbf from Palcomix"]
}
