{
"pu4rqsqa3e3ykv2lypbo2xtd":["bjtekj","Bjarne Kjeldsen"],
"m5hn47z6ffl2gsh2w7ysgk35":"bjt",
"7f3tefttlykzt2qt6rmka5q7":["bjthylacine","Bandie.J.Thylacine"],
"r4h7wd2pfaqfsfk6r7ek3pr5":["bjtm","Ben M"],
"tw2nqr4w2zglv6gcw2xkvneo":["bjthebear","A Civil Libertine"],
"sczv6i6eqavoyorb775ymjji":"bjtaylor",
"crx726eke4gomdldkk5psrh7":"bjtrustno1",
"ef47d3nbdo35efbdf6ejd3h5":"bjthom",
"x5rpx57u6vgjrxt3yc75cgba":"bjthesnail",
"ofsiu5oaalysecq4lttgnkqr":["bjtowan","もな"],
"dl73djlwfnzfilhs4drj3dzp":"bjthemole",
"whl4ouvzxjactoiuteqcmcxk":["thehandyman","BJThomasMA/MS"]
}
